oki/__init__.py
oki/main.py
oki/VERSION
oki-0.0.1.dist-info/DESCRIPTION.rst
oki-0.0.1.dist-info/METADATA
oki-0.0.1.dist-info/metadata.json
oki-0.0.1.dist-info/RECORD
oki-0.0.1.dist-info/top_level.txt
oki-0.0.1.dist-info/WHEEL
